[ 
{ "directory": "C:\\dev\\Bizz-App\\client", "file": "src/editor/ui.cpp", "output": "src/editor/ui.o", "arguments": ["C:\\LLVM\\bin\\clang++.exe", "-xc++", "src/editor/ui.cpp", "-o", "src/editor/ui.o", "--driver-mode=g++", "-c", "-std=c++20", "-I", "../lib/glm/", "-I", "../lib/imgui/", "-I", "tcp/", "-I", "../lib/glfw/include", "-I", "../lib/glad/include", "--target=x86_64-pc-windows-msvc19.38.33133"]},
{ "directory": "C:\\dev\\Bizz-App\\client", "file": "src/editor/window.cpp", "output": "src/editor/window.o", "arguments": ["C:\\LLVM\\bin\\clang++.exe", "-xc++", "src/editor/window.cpp", "-o", "src/editor/window.o", "--driver-mode=g++", "-c", "-std=c++20", "-I", "../lib/glm/", "-I", "../lib/imgui/", "-I", "tcp/", "-I", "../lib/glfw/include", "-I", "../lib/glad/include", "--target=x86_64-pc-windows-msvc19.38.33133"]},
{ "directory": "C:\\dev\\Bizz-App\\client", "file": "src/util/imgui_datechooser.cpp", "output": "src/util/imgui_datechooser.o", "arguments": ["C:\\LLVM\\bin\\clang++.exe", "-xc++", "src/util/imgui_datechooser.cpp", "-o", "src/util/imgui_datechooser.o", "--driver-mode=g++", "-c", "-std=c++20", "-I", "../lib/glm/", "-I", "../lib/imgui/", "-I", "tcp/", "-I", "../lib/glfw/include", "-I", "../lib/glad/include", "-Wno-deprecated-declarations", "--target=x86_64-pc-windows-msvc19.38.33133"]},
{ "directory": "C:\\dev\\Bizz-App\\client", "file": "src/util/tcp.cpp", "output": "src/util/tcp.o", "arguments": ["C:\\LLVM\\bin\\clang++.exe", "-xc++", "src/util/tcp.cpp", "-o", "src/util/tcp.o", "--driver-mode=g++", "-c", "-std=c++20", "-I", "../lib/glm/", "-I", "../lib/imgui/", "-I", "tcp/", "-I", "../lib/glfw/include", "-I", "../lib/glad/include", "--target=x86_64-pc-windows-msvc19.38.33133"]},
{ "directory": "C:\\dev\\Bizz-App\\client", "file": "src/util/util.cpp", "output": "src/util/util.o", "arguments": ["C:\\LLVM\\bin\\clang++.exe", "-xc++", "src/util/util.cpp", "-o", "src/util/util.o", "--driver-mode=g++", "-c", "-std=c++20", "-I", "../lib/glm/", "-I", "../lib/imgui/", "-I", "tcp/", "-I", "../lib/glfw/include", "-I", "../lib/glad/include", "-Wno-deprecated-declarations", "--target=x86_64-pc-windows-msvc19.38.33133"]},
{ "directory": "C:\\dev\\Bizz-App\\client", "file": "src/accounts.cpp", "output": "src/accounts.o", "arguments": ["C:\\LLVM\\bin\\clang++.exe", "-xc++", "src/accounts.cpp", "-o", "src/accounts.o", "--driver-mode=g++", "-c", "-std=c++20", "-I", "../lib/glm/", "-I", "../lib/imgui/", "-I", "tcp/", "-I", "../lib/glfw/include", "-I", "../lib/glad/include", "-Wno-deprecated-declarations", "--target=x86_64-pc-windows-msvc19.38.33133"]},
{ "directory": "C:\\dev\\Bizz-App\\client", "file": "src/context.cpp", "output": "src/context.o", "arguments": ["C:\\LLVM\\bin\\clang++.exe", "-xc++", "src/context.cpp", "-o", "src/context.o", "--driver-mode=g++", "-c", "-std=c++20", "-I", "../lib/glm/", "-I", "../lib/imgui/", "-I", "tcp/", "-I", "../lib/glfw/include", "-I", "../lib/glad/include", "-Wno-deprecated-declarations", "--target=x86_64-pc-windows-msvc19.38.33133"]},
{ "directory": "C:\\dev\\Bizz-App\\client", "file": "src/generators.cpp", "output": "src/generators.o", "arguments": ["C:\\LLVM\\bin\\clang++.exe", "-xc++", "src/generators.cpp", "-o", "src/generators.o", "--driver-mode=g++", "-c", "-std=c++20", "-I", "../lib/glm/", "-I", "../lib/imgui/", "-I", "tcp/", "-I", "../lib/glfw/include", "-I", "../lib/glad/include", "-Wno-deprecated-declarations", "--target=x86_64-pc-windows-msvc19.38.33133"]},
{ "directory": "C:\\dev\\Bizz-App\\client", "file": "src/main.cpp", "output": "src/main.o", "arguments": ["C:\\LLVM\\bin\\clang++.exe", "-xc++", "src/main.cpp", "-o", "src/main.o", "--driver-mode=g++", "-c", "-std=c++20", "-I", "../lib/glm/", "-I", "../lib/imgui/", "-I", "tcp/", "-I", "../lib/glfw/include", "-I", "../lib/glad/include", "-Wno-deprecated-declarations", "--target=x86_64-pc-windows-msvc19.38.33133"]},
{ "directory": "C:\\dev\\Bizz-App\\client", "file": "src/state.cpp", "output": "src/state.o", "arguments": ["C:\\LLVM\\bin\\clang++.exe", "-xc++", "src/state.cpp", "-o", "src/state.o", "--driver-mode=g++", "-c", "-std=c++20", "-I", "../lib/glm/", "-I", "../lib/imgui/", "-I", "tcp/", "-I", "../lib/glfw/include", "-I", "../lib/glad/include", "-Wno-deprecated-declarations", "--target=x86_64-pc-windows-msvc19.38.33133"]}
] 
